finitediffx/__init__.py
finitediffx/_src/__init__.py
finitediffx/_src/fgrad.py
finitediffx/_src/finite_diff.py
finitediffx/_src/utils.py
finitediffx-0.1.0.dist-info/LICENSE
finitediffx-0.1.0.dist-info/METADATA
finitediffx-0.1.0.dist-info/WHEEL
finitediffx-0.1.0.dist-info/top_level.txt
finitediffx-0.1.0.dist-info/RECORD
